astro_notebooks/__about__.py
astro_notebooks/__init__.py
astro_notebooks/_version.py
astro_notebooks/color-mixer-template.ipynb
astro_notebooks/image-viewers.ipynb
astro_notebooks/image_selector.py
astro_notebooks/light-image-combo-template.ipynb
astro_notebooks/quick-color-template.ipynb
astro_notebooks/reproject-images.ipynb
astro_notebooks-0.6.0.data/data/share/jupyter/astro_notebooks/__about__.py
astro_notebooks-0.6.0.data/data/share/jupyter/astro_notebooks/__init__.py
astro_notebooks-0.6.0.data/data/share/jupyter/astro_notebooks/_version.py
astro_notebooks-0.6.0.data/data/share/jupyter/astro_notebooks/color-mixer-template.ipynb
astro_notebooks-0.6.0.data/data/share/jupyter/astro_notebooks/image-viewers.ipynb
astro_notebooks-0.6.0.data/data/share/jupyter/astro_notebooks/image_selector.py
astro_notebooks-0.6.0.data/data/share/jupyter/astro_notebooks/light-image-combo-template.ipynb
astro_notebooks-0.6.0.data/data/share/jupyter/astro_notebooks/quick-color-template.ipynb
astro_notebooks-0.6.0.data/data/share/jupyter/astro_notebooks/reproject-images.ipynb
astro_notebooks-0.6.0.data/data/share/jupyter/jupyter_app_launcher/jp_app_launcher_astro-notebooks.yaml
astro_notebooks-0.6.0.dist-info/METADATA
astro_notebooks-0.6.0.dist-info/WHEEL
astro_notebooks-0.6.0.dist-info/licenses/LICENSE
astro_notebooks-0.6.0.dist-info/RECORD
