Metadata-Version: 2.3
Name: astro-notebooks
Version: 0.6.0
Project-URL: Documentation, https://github.com/feder-observatory/astro-notebooks#readme
Project-URL: Issues, https://github.com/feder-observatory/astro-notebooks/issues
Project-URL: Source, https://github.com/feder-observatory/astro-notebooks
Author-email: Matt Craig <mattwcraig@gmail.com>
License-Expression: BSD-3-Clause
License-File: LICENSE
Classifier: Development Status :: 4 - Beta
Classifier: Programming Language :: Python
Classifier: Programming Language :: Python :: 3.8
Classifier: Programming Language :: Python :: 3.9
Classifier: Programming Language :: Python :: 3.10
Classifier: Programming Language :: Python :: 3.11
Classifier: Programming Language :: Python :: 3.12
Classifier: Programming Language :: Python :: Implementation :: CPython
Classifier: Programming Language :: Python :: Implementation :: PyPy
Requires-Python: >=3.11
Requires-Dist: jupyter-app-launcher
Requires-Dist: stellarphot
